[
    {
        "group": "Fancode | LIVE",
        "logo": "https://www.fancode.com/skillup-uploads/cms-media/138243_5765_IN-A_UAE_fc-web_1763068129174.jpg",
        "mobile": "on",
        "name": "India A vs United Arab Emirates (ACC Asia Cup Rising Stars 2025)",
        "premium": false,
        "source": {
            "headers": {
                "User-Agent": "Mozilla/5.0 (Windows NT 10.0; Win64; x64) AppleWebKit/537.36 (KHTML, like Gecko) Chrome/121.0.0.0 ygx/69.1 Safari/537.36"
            },
            "url": "https://sonypartnersdaimenew.akamaized.net/hls/live/2022318/DAI24ME-ACRSM/master.m3u8?hdnea=exp=1763162741~acl=/*~id=64265660912735607501577113591518~hmac=d209f0728774515c69da06137b14cf2136e3ee66b7bf7d2c04d0a991d0a00c93"
        },
        "status": "on",
        "tv": "off"
    },
    {
        "group": "Fancode | LIVE",
        "logo": "https://www.fancode.com/skillup-uploads/cms-media/Motul-Grand-Prix-of-the-Valencian-Community-old-match-card-.png",
        "mobile": "on",
        "name": "Day 1 vs Circuit Ricardo Tormo (MOTUL GRAND PRIX OF THE VALENCIAN COMMUNITY)",
        "premium": false,
        "source": {
            "headers": {
                "User-Agent": "Mozilla/5.0 (Windows NT 10.0; Win64; x64) AppleWebKit/537.36 (KHTML, like Gecko) Chrome/121.0.0.0 ygx/69.1 Safari/537.36"
            },
            "url": "https://bd-mc-fdlive.fancode.com/mumbai/119293_english_hls_db2cad252b95519_1ta-di_h264/index.m3u8"
        },
        "status": "on",
        "tv": "off"
    },
    {
        "group": "Fancode | UPCOMING",
        "logo": "https://www.fancode.com/skillup-uploads/cms-media/138244_5765_BN-A_HK_fc-web_1763068128414.jpg",
        "mobile": "on",
        "name": "Bangladesh A vs Hong Kong, China (ACC Asia Cup Rising Stars 2025)",
        "premium": false,
        "source": {
            "headers": {
                "User-Agent": "Mozilla/5.0 (Windows NT 10.0; Win64; x64) AppleWebKit/537.36 (KHTML, like Gecko) Chrome/121.0.0.0 ygx/69.1 Safari/537.36"
            },
            "url": ""
        },
        "status": "on",
        "tv": "off"
    },
    {
        "group": "Fancode | UPCOMING",
        "logo": "https://www.fancode.com/skillup-uploads/cms-media/133941_5606_TAS_SAU_fc-web.jpg",
        "mobile": "on",
        "name": "Tasmania vs South Australia (One Day Cup, 2025-26)",
        "premium": false,
        "source": {
            "headers": {
                "User-Agent": "Mozilla/5.0 (Windows NT 10.0; Win64; x64) AppleWebKit/537.36 (KHTML, like Gecko) Chrome/121.0.0.0 ygx/69.1 Safari/537.36"
            },
            "url": ""
        },
        "status": "on",
        "tv": "off"
    },
    {
        "group": "Fancode | UPCOMING",
        "logo": "https://www.fancode.com/skillup-uploads/cms-media/138245_5765_SL-A_AF-A_fc-web_1763068128437.jpg",
        "mobile": "on",
        "name": "Sri Lanka A vs Afghanistan A (ACC Asia Cup Rising Stars 2025)",
        "premium": false,
        "source": {
            "headers": {
                "User-Agent": "Mozilla/5.0 (Windows NT 10.0; Win64; x64) AppleWebKit/537.36 (KHTML, like Gecko) Chrome/121.0.0.0 ygx/69.1 Safari/537.36"
            },
            "url": ""
        },
        "status": "on",
        "tv": "off"
    },
    {
        "group": "Fancode | UPCOMING",
        "logo": "https://images.fancode.com/aig/match/v1/138060_CASACARDS_APP.png",
        "mobile": "on",
        "name": "Real Valladolid vs Las Palmas (LALIGA Hypermotion 2025-26)",
        "premium": false,
        "source": {
            "headers": {
                "User-Agent": "Mozilla/5.0 (Windows NT 10.0; Win64; x64) AppleWebKit/537.36 (KHTML, like Gecko) Chrome/121.0.0.0 ygx/69.1 Safari/537.36"
            },
            "url": ""
        },
        "status": "on",
        "tv": "off"
    },
    {
        "group": "Fancode | UPCOMING",
        "logo": "https://www.fancode.com/skillup-uploads/cms-media/137956_5744_SUW_VER-W_fc-web_1763103330946.jpg",
        "mobile": "on",
        "name": "Suwon FC vs Tokyo Verdy Beleza (AFC Women's Champions League 2025-26)",
        "premium": false,
        "source": {
            "headers": {
                "User-Agent": "Mozilla/5.0 (Windows NT 10.0; Win64; x64) AppleWebKit/537.36 (KHTML, like Gecko) Chrome/121.0.0.0 ygx/69.1 Safari/537.36"
            },
            "url": ""
        },
        "status": "on",
        "tv": "off"
    },
    {
        "group": "Fancode | UPCOMING",
        "logo": "https://www.fancode.com/skillup-uploads/cms-media/137957_5744_NAE-W_ISP-W_fc-web_1763103330289.jpg",
        "mobile": "on",
        "name": "Naegohyang Women's FC vs ISPE WFC (AFC Women's Champions League 2025-26)",
        "premium": false,
        "source": {
            "headers": {
                "User-Agent": "Mozilla/5.0 (Windows NT 10.0; Win64; x64) AppleWebKit/537.36 (KHTML, like Gecko) Chrome/121.0.0.0 ygx/69.1 Safari/537.36"
            },
            "url": ""
        },
        "status": "on",
        "tv": "off"
    },
    {
        "group": "Fancode | UPCOMING",
        "logo": "https://www.fancode.com/skillup-uploads/cms-media/Butterfield-Bermuda-Championship_2025_match-card_OLd_match-card.jpg",
        "mobile": "on",
        "name": "Day 2 vs Port Royal Golf Course - Southampton, Bermuda (Butterfield Bermuda Championship)",
        "premium": false,
        "source": {
            "headers": {
                "User-Agent": "Mozilla/5.0 (Windows NT 10.0; Win64; x64) AppleWebKit/537.36 (KHTML, like Gecko) Chrome/121.0.0.0 ygx/69.1 Safari/537.36"
            },
            "url": ""
        },
        "status": "on",
        "tv": "off"
    },
    {
        "group": "Fancode | UPCOMING",
        "logo": "https://www.fancode.com/skillup-uploads/cms-media/DP-WORLD_Old_match-card_2.jpg",
        "mobile": "on",
        "name": "Day 3 vs Jumeirah Golf Estates, Earth Course (DP World Tour Championship, Dubai)",
        "premium": false,
        "source": {
            "headers": {
                "User-Agent": "Mozilla/5.0 (Windows NT 10.0; Win64; x64) AppleWebKit/537.36 (KHTML, like Gecko) Chrome/121.0.0.0 ygx/69.1 Safari/537.36"
            },
            "url": ""
        },
        "status": "on",
        "tv": "off"
    },
    {
        "group": "Fancode | UPCOMING",
        "logo": "https://www.fancode.com/skillup-uploads/cms-media/Motul-Grand-Prix-of-the-Valencian-Community-old-match-card-.png",
        "mobile": "on",
        "name": "Day 2 vs Circuit Ricardo Tormo (MOTUL GRAND PRIX OF THE VALENCIAN COMMUNITY)",
        "premium": false,
        "source": {
            "headers": {
                "User-Agent": "Mozilla/5.0 (Windows NT 10.0; Win64; x64) AppleWebKit/537.36 (KHTML, like Gecko) Chrome/121.0.0.0 ygx/69.1 Safari/537.36"
            },
            "url": ""
        },
        "status": "on",
        "tv": "off"
    },
    {
        "group": "Fancode | UPCOMING",
        "logo": "https://www.fancode.com/skillup-uploads/cms-media/League-Two-2025-26_match-card.jpg",
        "mobile": "on",
        "name": "Gillingham vs Crawley Town FC (League Two 2025-26)",
        "premium": false,
        "source": {
            "headers": {
                "User-Agent": "Mozilla/5.0 (Windows NT 10.0; Win64; x64) AppleWebKit/537.36 (KHTML, like Gecko) Chrome/121.0.0.0 ygx/69.1 Safari/537.36"
            },
            "url": ""
        },
        "status": "on",
        "tv": "off"
    },
    {
        "group": "Fancode | UPCOMING",
        "logo": "https://www.fancode.com/skillup-uploads/cms-media/Racing-Club_vs_Granada_Old.jpg",
        "mobile": "on",
        "name": "Racing Club vs Granada (LALIGA Hypermotion 2025-26)",
        "premium": false,
        "source": {
            "headers": {
                "User-Agent": "Mozilla/5.0 (Windows NT 10.0; Win64; x64) AppleWebKit/537.36 (KHTML, like Gecko) Chrome/121.0.0.0 ygx/69.1 Safari/537.36"
            },
            "url": ""
        },
        "status": "on",
        "tv": "off"
    },
    {
        "group": "Fancode | UPCOMING",
        "logo": "https://www.fancode.com/skillup-uploads/cms-media/Butterfield-Bermuda-Championship_2025_match-card_OLd_match-card.jpg",
        "mobile": "on",
        "name": "Day 3 vs Port Royal Golf Course - Southampton, Bermuda (Butterfield Bermuda Championship)",
        "premium": false,
        "source": {
            "headers": {
                "User-Agent": "Mozilla/5.0 (Windows NT 10.0; Win64; x64) AppleWebKit/537.36 (KHTML, like Gecko) Chrome/121.0.0.0 ygx/69.1 Safari/537.36"
            },
            "url": ""
        },
        "status": "on",
        "tv": "off"
    },
    {
        "group": "Fancode | UPCOMING",
        "logo": "https://www.fancode.com/skillup-uploads/cms-media/WI-vs-NZ_ODIs_old.jpg",
        "mobile": "on",
        "name": "New Zealand vs West Indies (West Indies tour of New Zealand, 2025)",
        "premium": false,
        "source": {
            "headers": {
                "User-Agent": "Mozilla/5.0 (Windows NT 10.0; Win64; x64) AppleWebKit/537.36 (KHTML, like Gecko) Chrome/121.0.0.0 ygx/69.1 Safari/537.36"
            },
            "url": ""
        },
        "status": "on",
        "tv": "off"
    },
    {
        "group": "Fancode | UPCOMING",
        "logo": "https://www.fancode.com/skillup-uploads/cms-media/138246_5765_UAE_OMN_fc-web_1763068129254.jpg",
        "mobile": "on",
        "name": "United Arab Emirates vs Oman (ACC Asia Cup Rising Stars 2025)",
        "premium": false,
        "source": {
            "headers": {
                "User-Agent": "Mozilla/5.0 (Windows NT 10.0; Win64; x64) AppleWebKit/537.36 (KHTML, like Gecko) Chrome/121.0.0.0 ygx/69.1 Safari/537.36"
            },
            "url": ""
        },
        "status": "on",
        "tv": "off"
    },
    {
        "group": "Fancode | UPCOMING",
        "logo": "https://www.fancode.com/skillup-uploads/cms-media/137952_5744_SL_MLC-W_fc-web_1763103330221.jpg",
        "mobile": "on",
        "name": "Stallion Laguna vs Melbourne City Women (AFC Women's Champions League 2025-26)",
        "premium": false,
        "source": {
            "headers": {
                "User-Agent": "Mozilla/5.0 (Windows NT 10.0; Win64; x64) AppleWebKit/537.36 (KHTML, like Gecko) Chrome/121.0.0.0 ygx/69.1 Safari/537.36"
            },
            "url": ""
        },
        "status": "on",
        "tv": "off"
    },
    {
        "group": "Fancode | UPCOMING",
        "logo": "https://www.fancode.com/skillup-uploads/cms-media/DP-WORLD_Old_match-card_2.jpg",
        "mobile": "on",
        "name": "Day 4 vs Jumeirah Golf Estates, Earth Course (DP World Tour Championship, Dubai)",
        "premium": false,
        "source": {
            "headers": {
                "User-Agent": "Mozilla/5.0 (Windows NT 10.0; Win64; x64) AppleWebKit/537.36 (KHTML, like Gecko) Chrome/121.0.0.0 ygx/69.1 Safari/537.36"
            },
            "url": ""
        },
        "status": "on",
        "tv": "off"
    },
    {
        "group": "Fancode | UPCOMING",
        "logo": "https://www.fancode.com/skillup-uploads/cms-media/IN-vs-PAK_web.jpg",
        "mobile": "on",
        "name": "India A vs Pakistan Shaheens (ACC Asia Cup Rising Stars 2025)",
        "premium": false,
        "source": {
            "headers": {
                "User-Agent": "Mozilla/5.0 (Windows NT 10.0; Win64; x64) AppleWebKit/537.36 (KHTML, like Gecko) Chrome/121.0.0.0 ygx/69.1 Safari/537.36"
            },
            "url": ""
        },
        "status": "on",
        "tv": "off"
    },
    {
        "group": "Fancode | UPCOMING",
        "logo": "https://www.fancode.com/skillup-uploads/cms-media/eng_wi_old_match-card_2.jpg",
        "mobile": "on",
        "name": "West Indies Under-19 vs England Under-19 (England Under-19 tour of West Indies, 2025)",
        "premium": false,
        "source": {
            "headers": {
                "User-Agent": "Mozilla/5.0 (Windows NT 10.0; Win64; x64) AppleWebKit/537.36 (KHTML, like Gecko) Chrome/121.0.0.0 ygx/69.1 Safari/537.36"
            },
            "url": ""
        },
        "status": "on",
        "tv": "off"
    },
    {
        "group": "Fancode | UPCOMING",
        "logo": "https://www.fancode.com/skillup-uploads/cms-media/137953_5744_LIO_HCMC_fc-web_1763103330920.jpg",
        "mobile": "on",
        "name": "Lion City Sailors vs Ho Chi Minh City Women\u2019s FC (AFC Women's Champions League 2025-26)",
        "premium": false,
        "source": {
            "headers": {
                "User-Agent": "Mozilla/5.0 (Windows NT 10.0; Win64; x64) AppleWebKit/537.36 (KHTML, like Gecko) Chrome/121.0.0.0 ygx/69.1 Safari/537.36"
            },
            "url": ""
        },
        "status": "on",
        "tv": "off"
    },
    {
        "group": "Fancode | UPCOMING",
        "logo": "https://www.fancode.com/skillup-uploads/cms-media/Motul-Grand-Prix-of-the-Valencian-Community-old-match-card-.png",
        "mobile": "on",
        "name": "Race Day vs Circuit Ricardo Tormo (MOTUL GRAND PRIX OF THE VALENCIAN COMMUNITY)",
        "premium": false,
        "source": {
            "headers": {
                "User-Agent": "Mozilla/5.0 (Windows NT 10.0; Win64; x64) AppleWebKit/537.36 (KHTML, like Gecko) Chrome/121.0.0.0 ygx/69.1 Safari/537.36"
            },
            "url": ""
        },
        "status": "on",
        "tv": "off"
    },
    {
        "group": "Fancode | UPCOMING",
        "logo": "https://www.fancode.com/skillup-uploads/cms-media/Football_Fallback_Old_match-card.jpg",
        "mobile": "on",
        "name": "Nigeria vs DR Congo (CAF World Cup Qualifiers)",
        "premium": false,
        "source": {
            "headers": {
                "User-Agent": "Mozilla/5.0 (Windows NT 10.0; Win64; x64) AppleWebKit/537.36 (KHTML, like Gecko) Chrome/121.0.0.0 ygx/69.1 Safari/537.36"
            },
            "url": ""
        },
        "status": "on",
        "tv": "off"
    },
    {
        "group": "Fancode | UPCOMING",
        "logo": "https://www.fancode.com/skillup-uploads/cms-media/Butterfield-Bermuda-Championship_2025_match-card_OLd_match-card.jpg",
        "mobile": "on",
        "name": "Day 4 vs Port Royal Golf Course - Southampton, Bermuda (Butterfield Bermuda Championship)",
        "premium": false,
        "source": {
            "headers": {
                "User-Agent": "Mozilla/5.0 (Windows NT 10.0; Win64; x64) AppleWebKit/537.36 (KHTML, like Gecko) Chrome/121.0.0.0 ygx/69.1 Safari/537.36"
            },
            "url": ""
        },
        "status": "on",
        "tv": "off"
    },
    {
        "group": "Fancode | UPCOMING",
        "logo": "https://images.fancode.com/aig/match/v1/138063_CASACARDS_APP.png",
        "mobile": "on",
        "name": "Real Zaragoza vs Huesca (LALIGA Hypermotion 2025-26)",
        "premium": false,
        "source": {
            "headers": {
                "User-Agent": "Mozilla/5.0 (Windows NT 10.0; Win64; x64) AppleWebKit/537.36 (KHTML, like Gecko) Chrome/121.0.0.0 ygx/69.1 Safari/537.36"
            },
            "url": ""
        },
        "status": "on",
        "tv": "off"
    },
    {
        "group": "Fancode | UPCOMING",
        "logo": "https://www.fancode.com/skillup-uploads/cms-media/138248_5765_SL-A_HK_fc-web_1763068128435.jpg",
        "mobile": "on",
        "name": "Sri Lanka A vs Hong Kong, China (ACC Asia Cup Rising Stars 2025)",
        "premium": false,
        "source": {
            "headers": {
                "User-Agent": "Mozilla/5.0 (Windows NT 10.0; Win64; x64) AppleWebKit/537.36 (KHTML, like Gecko) Chrome/121.0.0.0 ygx/69.1 Safari/537.36"
            },
            "url": ""
        },
        "status": "on",
        "tv": "off"
    },
    {
        "group": "Fancode | UPCOMING",
        "logo": "https://www.fancode.com/skillup-uploads/cms-media/137948_5744_BKFC_EBFC_fc-web_1763103330908.jpg",
        "mobile": "on",
        "name": "Bam Khatoon FC vs East Bengal (AFC Women's Champions League 2025-26)",
        "premium": false,
        "source": {
            "headers": {
                "User-Agent": "Mozilla/5.0 (Windows NT 10.0; Win64; x64) AppleWebKit/537.36 (KHTML, like Gecko) Chrome/121.0.0.0 ygx/69.1 Safari/537.36"
            },
            "url": ""
        },
        "status": "on",
        "tv": "off"
    },
    {
        "group": "Fancode | UPCOMING",
        "logo": "https://images.fancode.com/aig/match/v1/138293_CASACARDS_APP.png",
        "mobile": "on",
        "name": "Janakpur Bolts vs Kathmandu Gurkhas (Nepal Premier League, 2025)",
        "premium": false,
        "source": {
            "headers": {
                "User-Agent": "Mozilla/5.0 (Windows NT 10.0; Win64; x64) AppleWebKit/537.36 (KHTML, like Gecko) Chrome/121.0.0.0 ygx/69.1 Safari/537.36"
            },
            "url": ""
        },
        "status": "on",
        "tv": "off"
    },
    {
        "group": "Fancode | UPCOMING",
        "logo": "https://www.fancode.com/skillup-uploads/cms-media/137949_5744_WJ-W_NAS-W_fc-web_1763103330280.jpg",
        "mobile": "on",
        "name": "Wuhan Jiangda Women vs PFC Nasaf (AFC Women's Champions League 2025-26)",
        "premium": false,
        "source": {
            "headers": {
                "User-Agent": "Mozilla/5.0 (Windows NT 10.0; Win64; x64) AppleWebKit/537.36 (KHTML, like Gecko) Chrome/121.0.0.0 ygx/69.1 Safari/537.36"
            },
            "url": ""
        },
        "status": "on",
        "tv": "off"
    },
    {
        "group": "Fancode | UPCOMING",
        "logo": "https://www.fancode.com/skillup-uploads/cms-media/138249_5765_BN-A_AF-A_fc-web_1763068128416.jpg",
        "mobile": "on",
        "name": "Bangladesh A vs Afghanistan A (ACC Asia Cup Rising Stars 2025)",
        "premium": false,
        "source": {
            "headers": {
                "User-Agent": "Mozilla/5.0 (Windows NT 10.0; Win64; x64) AppleWebKit/537.36 (KHTML, like Gecko) Chrome/121.0.0.0 ygx/69.1 Safari/537.36"
            },
            "url": ""
        },
        "status": "on",
        "tv": "off"
    },
    {
        "group": "Fancode | UPCOMING",
        "logo": "https://images.fancode.com/aig/match/v1/138064_CASACARDS_APP.png",
        "mobile": "on",
        "name": "Cultural Leonesa vs M\u00e1laga (LALIGA Hypermotion 2025-26)",
        "premium": false,
        "source": {
            "headers": {
                "User-Agent": "Mozilla/5.0 (Windows NT 10.0; Win64; x64) AppleWebKit/537.36 (KHTML, like Gecko) Chrome/121.0.0.0 ygx/69.1 Safari/537.36"
            },
            "url": ""
        },
        "status": "on",
        "tv": "off"
    },
    {
        "group": "Fancode | UPCOMING",
        "logo": "https://www.fancode.com/skillup-uploads/cms-media/Cricket_Fallback_Old_match-card.jpg",
        "mobile": "on",
        "name": "Indonesia vs Bahrain (Bahrain tour of Indonesia, 2025)",
        "premium": false,
        "source": {
            "headers": {
                "User-Agent": "Mozilla/5.0 (Windows NT 10.0; Win64; x64) AppleWebKit/537.36 (KHTML, like Gecko) Chrome/121.0.0.0 ygx/69.1 Safari/537.36"
            },
            "url": ""
        },
        "status": "on",
        "tv": "off"
    },
    {
        "group": "Fancode | UPCOMING",
        "logo": "https://images.fancode.com/aig/match/v1/138294_CASACARDS_APP.png",
        "mobile": "on",
        "name": "Chitwan Rhinos vs Karnali Yaks (Nepal Premier League, 2025)",
        "premium": false,
        "source": {
            "headers": {
                "User-Agent": "Mozilla/5.0 (Windows NT 10.0; Win64; x64) AppleWebKit/537.36 (KHTML, like Gecko) Chrome/121.0.0.0 ygx/69.1 Safari/537.36"
            },
            "url": ""
        },
        "status": "on",
        "tv": "off"
    },
    {
        "group": "Fancode | UPCOMING",
        "logo": "https://www.fancode.com/skillup-uploads/cms-media/138250_5765_PKS_UAE_fc-web_1763068128496.jpg",
        "mobile": "on",
        "name": "Pakistan Shaheens vs United Arab Emirates (ACC Asia Cup Rising Stars 2025)",
        "premium": false,
        "source": {
            "headers": {
                "User-Agent": "Mozilla/5.0 (Windows NT 10.0; Win64; x64) AppleWebKit/537.36 (KHTML, like Gecko) Chrome/121.0.0.0 ygx/69.1 Safari/537.36"
            },
            "url": ""
        },
        "status": "on",
        "tv": "off"
    },
    {
        "group": "Fancode | UPCOMING",
        "logo": "https://images.fancode.com/aig/match/v1/138295_CASACARDS_APP.png",
        "mobile": "on",
        "name": "Biratnagar Kings vs Pokhara Avengers (Nepal Premier League, 2025)",
        "premium": false,
        "source": {
            "headers": {
                "User-Agent": "Mozilla/5.0 (Windows NT 10.0; Win64; x64) AppleWebKit/537.36 (KHTML, like Gecko) Chrome/121.0.0.0 ygx/69.1 Safari/537.36"
            },
            "url": ""
        },
        "status": "on",
        "tv": "off"
    },
    {
        "group": "Fancode | UPCOMING",
        "logo": "https://www.fancode.com/skillup-uploads/cms-media/138203_5763_QQY_NW_fc-web.png",
        "mobile": "on",
        "name": "Quetta Qavalry vs Northern Warriors (Abu Dhabi T10, 2025)",
        "premium": false,
        "source": {
            "headers": {
                "User-Agent": "Mozilla/5.0 (Windows NT 10.0; Win64; x64) AppleWebKit/537.36 (KHTML, like Gecko) Chrome/121.0.0.0 ygx/69.1 Safari/537.36"
            },
            "url": ""
        },
        "status": "on",
        "tv": "off"
    }
]